csv_tabulator/__init__.py
csv_tabulator/converter.py
csv_tabulator/requirements.txt
csv_tabulator-1.0.1.dist-info/METADATA
csv_tabulator-1.0.1.dist-info/WHEEL
csv_tabulator-1.0.1.dist-info/licenses/LICENSE
csv_tabulator-1.0.1.dist-info/RECORD
