Metadata-Version: 2.1
Name: csv_tabulator
Version: 1.0.1
Summary: Convert the csv to html table
Project-URL: Homepage, https://github.com/amiaynara/csv-tabulator
Project-URL: Bug Tracker, https://github.com/amiaynara/csv-tabulator/issues
Author-email: Amiay Narayan <amiay.narayan@gmail.com>
License-File: LICENSE
Classifier: License :: OSI Approved :: MIT License
Classifier: Operating System :: OS Independent
Classifier: Programming Language :: Python :: 3
Requires-Python: >=3.7
